{
"meta":{"test_sets":[],"test_metrics":[],"learn_metrics":[{"best_value":"Min","name":"RMSE"}],"launch_mode":"Train","parameters":"","iteration_count":500,"learn_sets":["learn"],"name":"experiment"},
"iterations":[
{"learn":[11.31319641],"iteration":0,"passed_time":0.1423483046,"remaining_time":71.03180398},
{"learn":[10.12681957],"iteration":1,"passed_time":0.1441264704,"remaining_time":35.88749112},
{"learn":[9.750125492],"iteration":2,"passed_time":0.1468287578,"remaining_time":24.32463087},
{"learn":[9.405141742],"iteration":3,"passed_time":0.1502226602,"remaining_time":18.62760987},
{"learn":[9.063428053],"iteration":4,"passed_time":0.1527475075,"remaining_time":15.12200324},
{"learn":[8.727404973],"iteration":5,"passed_time":0.1555603782,"remaining_time":12.80780447},
{"learn":[8.400390345],"iteration":6,"passed_time":0.1579982999,"remaining_time":11.12759455},
{"learn":[8.079149347],"iteration":7,"passed_time":0.1599540518,"remaining_time":9.837174187},
{"learn":[8.366427395],"iteration":8,"passed_time":0.1646940255,"remaining_time":8.984974057},
{"learn":[8.077326038],"iteration":9,"passed_time":0.1759732524,"remaining_time":8.622689367},
{"learn":[7.769818121],"iteration":10,"passed_time":0.1811673779,"remaining_time":8.053713436},
{"learn":[7.495408448],"iteration":11,"passed_time":0.1888349636,"remaining_time":7.67928852},
{"learn":[7.233477986],"iteration":12,"passed_time":0.1934598194,"remaining_time":7.247302466},
{"learn":[6.956346025],"iteration":13,"passed_time":0.1982893401,"remaining_time":6.883472807},
{"learn":[6.701693631],"iteration":14,"passed_time":0.2027961632,"remaining_time":6.557075942},
{"learn":[6.448014178],"iteration":15,"passed_time":0.2072329011,"remaining_time":6.268795258},
{"learn":[6.226257173],"iteration":16,"passed_time":0.2144194019,"remaining_time":6.092033595},
{"learn":[5.99574869],"iteration":17,"passed_time":0.2274039218,"remaining_time":6.089371684},
{"learn":[5.800422621],"iteration":18,"passed_time":0.2339635106,"remaining_time":5.922970978},
{"learn":[5.610678146],"iteration":19,"passed_time":0.2408971551,"remaining_time":5.781531723},
{"learn":[5.43712149],"iteration":20,"passed_time":0.2449858101,"remaining_time":5.588009668},
{"learn":[5.256791816],"iteration":21,"passed_time":0.2537140519,"remaining_time":5.5125144},
{"learn":[5.089585666],"iteration":22,"passed_time":0.2650352219,"remaining_time":5.496600038},
{"learn":[4.920777527],"iteration":23,"passed_time":0.2685128281,"remaining_time":5.325504425},
{"learn":[4.781684751],"iteration":24,"passed_time":0.2734429083,"remaining_time":5.195415258},
{"learn":[4.631730915],"iteration":25,"passed_time":0.2766684432,"remaining_time":5.043878542},
{"learn":[4.477856218],"iteration":26,"passed_time":0.2812006543,"remaining_time":4.926218869},
{"learn":[4.322245283],"iteration":27,"passed_time":0.2842489173,"remaining_time":4.791624605},
{"learn":[4.187500022],"iteration":28,"passed_time":0.2920324953,"remaining_time":4.743010527},
{"learn":[4.055381871],"iteration":29,"passed_time":0.297394278,"remaining_time":4.659177022},
{"learn":[3.913013433],"iteration":30,"passed_time":0.3034485563,"remaining_time":4.590882996},
{"learn":[3.783953951],"iteration":31,"passed_time":0.3076852935,"remaining_time":4.499897417},
{"learn":[3.678590138],"iteration":32,"passed_time":0.3162205671,"remaining_time":4.475000147},
{"learn":[3.567878424],"iteration":33,"passed_time":0.3235874724,"remaining_time":4.435051828},
{"learn":[3.465371318],"iteration":34,"passed_time":0.3289911482,"remaining_time":4.370882398},
{"learn":[3.367660753],"iteration":35,"passed_time":0.3322044604,"remaining_time":4.281746378},
{"learn":[3.279074595],"iteration":36,"passed_time":0.3402811213,"remaining_time":4.25811241},
{"learn":[3.182518649],"iteration":37,"passed_time":0.3419822379,"remaining_time":4.15778405},
{"learn":[3.097222981],"iteration":38,"passed_time":0.3434168646,"remaining_time":4.0593,
{"le,
{"learn":[3.007210004],"iteration":39,"passed_time":0.3448648335,"remaining_time":3.96,
,
{"learn":[2.934925358],"iteration":40,"passed_time":0.3601069458,"remaining_time":4.03144117,
,
{"learn":[2.849620505],"iteration":41,"passed_time":0.3641482904,"remaining_time":3.97095040,
,
{"learn":[2.775476948],"iteration":42,"passed_time":0.3722128704,"remaining_time":3.955843762},
{"learn":[2.694630348],"iteration":43,"passed_time":0.3772966122,"remaining_time":3.91016489},
{"learn":[2.624365401],"iteration":44,"passed_time":0.3836803439,"remaining_time":3.879434589},
{"learn":[2.557219463],"iteration":45,"passed_time":0.3864973879,"remaining_time":3.814561176},
{"learn":[2.500771904],"iteration":46,"passed_time":0.391674127,"remaining_time":3.775071905},
{"learn":[2.43104623],"iteration":47,"passed_time":0.3936601845,"remaining_time":3.706966737},
{"learn":[2.364831872],"iteration":48,"passed_time":0.396012508,"remaining_time":3.644931,
{",
{"learn":[2.318350384],"iteration":49,"passed_time":0.4047638492,"remaining_time":3.642874643},
{"learn":[2.26224128],"iteration":50,"passed_time":0.4077143907,"remaining_time":3.5894855,
{,
{"learn":[2.210178483],"iteration":51,"passed_time":0.4136193266,"remaining_time":3.563489583},
{"learn":[2.160913486],"iteration":52,"passed_time":0.4165512851,"remaining_time":3.51317782},
{"learn":[2.123431298],"iteration":53,"passed_time":0.4191472608,"remaining_time":3.46184589,
,
{"learn":[2.072716493],"iteration":54,"passed_time":0.4223477732,"remaining_time":3.41717743,
{"learn":[1.969446104],"iteration":55,"passed_time":0.4260963274,"remaining_time":3.378335168},
{"learn":[1.983289151],"iteration":56,"passed_time":0.4353297671,"remaining_time":3.3833524},
{"learn":[1.935808421],"iteration":57,"passed_time":0.4408291058,"remaining_time":3.359421806},
{"learn":[1.897433188],"iteration":58,"passed_time":0.4472788088,"remaining_time":3.343219571},
{"learn":[1.86207111],"iteration":59,"passed_time":0.4520920818,"remaining_time":3.315341933},
{"learn":[1.821732407],"iteration":60,"passed_time":0.4568209676,"remaining_time":3.287613193},
{"learn":[1.788974213],"iteration":61,"passed_time":0.4612666453,"remaining_time":3.258625656},
{"learn":[1.749582631],"iteration":62,"passed_time":0.4646285705,"remaining_time":3.222899767},
{"learn":[1.7133868],"iteration":63,"passed_time":0.4680683497,"remaining_time":3.188715632},
{"learn":[1.683520896],"iteration":64,"passed_time":0.472975647,"remaining_time":3.16529856},
{"learn":[1.648556829],"iteration":65,"passed_time":0.4753083731,"remaining_time":3.125512635},
{"learn":[1.630656572],"iteration":66,"passed_time":0.4788879677,"remaining_time":3.094902836},
{"learn":[1.609648041],"iteration":67,"passed_time":0.4828597537,"remaining_time":3.067579612},
{"learn":[1.583770575],"iteration":68,"passed_time":0.4853455976,"remaining_time":3.031651486},
{"learn":[1.572582601],"iteration":69,"passed_time":0.4863635019,"remaining_time":2.987661511},
{"learn":[1.561523458],"iteration":70,"passed_time":0.4870327178,"remaining_time":2.942775154},
{"learn":[1.537477486],"iteration":71,"passed_time":0.4904921418,"remaining_time":2.915703287},
{"learn":[1.514486878],"iteration":72,"passed_time":0.4959873834,"remaining_time":2.901186475},
{"learn":[1.487839876],"iteration":73,"passed_time":0.5002702473,"remaining_time":2.879934126},
{"learn":[1.465274907],"iteration":74,"passed_time":0.5031430268,"remaining_time":2.851143819},
{"learn":[1.454517868],"iteration":75,"passed_time":0.50516476,"remaining_time":2.818287608},
{"learn":[1.428310482],"iteration":76,"passed_time":0.5088331073,"remaining_time":2.795277979},
{"learn":[1.402732484],"iteration":77,"passed_time":0.5106919914,"remaining_time":2.76297462},
{"learn":[1.389340509],"iteration":78,"passed_time":0.5130409445,"remaining_time":2.734053641},
{"learn":[1.367614379],"iteration":79,"passed_time":0.5154404149,"remaining_time":2.706062178},
{"le,
{"learn":[1.346476114],"iteration":80,"passed_time":0.5173912975,"remaining_time":2.6763,
{"le,
{"learn":[1.33524912],"iteration":81,"passed_time":0.520268315,"remaining_time":2.65209,
{"l,
{"learn":[1.325974215],"iteration":82,"passed_time":0.5238969216,"remaining_time":2.63210863},
{"learn":[1.305267544],"iteration":83,"passed_time":0.5270743925,"remaining_time":2.610273182},
{"learn":[1.288739286],"iteration":84,"passed_time":0.5320005773,"remaining_time":2.597414583},
{"learn":[1.273517516],"iteration":85,"passed_time":0.537262625,"remaining_time":2.586357288},
{"learn":[1.261142892],"iteration":86,"passed_time":0.5405132114,"remaining_time":2.565884555},
{"learn":[1.248327198],"iteration":87,"passed_time":0.5433579705,"remaining_time":2.543903225},
{"learn":[1.241257157],"iteration":88,"passed_time":0.545721376,"remaining_time":2.520129051},
{"learn":[1.230191758],"iteration":89,"passed_time":0.5487626866,"remaining_time":2.499918906},
{"learn":[1.220998398],"iteration":90,"passed_time":0.5516661615,"remaining_time":2.479466594},
{"learn":[1.209096277],"iteration":91,"passed_time":0.553978679,"remaining_time":2.456775011},
{"learn":[1.200377305],"iteration":92,"passed_time":0.5566123319,"remaining_time":2.435927087},
{"learn":[1.193060121],"iteration":93,"passed_time":0.5617636594,"remaining_time":2.426340912},
{"learn":[1.17898621],"iteration":94,"passed_time":0.5678917894,"remaining_time":2.421012365},
{"learn":[1.162260128],"iteration":95,"passed_time":0.5696248756,"remaining_time":2.397171,
{",
{"learn":[1.15665938],"iteration":96,"passed_time":0.5732205581,"remaining_time":2.3815245,
{,
{"learn":[1.146997498],"iteration":97,"passed_time":0.5780999706,"remaining_time":2.3713896,
{,
{"learn":[1.137323799],"iteration":98,"passed_time":0.5862710441,"remaining_time":2.374693825},
{"learn":[1.125406643],"iteration":99,"passed_time":0.5911896004,"remaining_time":2.364758402},
{"learn":[1.114440709],"iteration":100,"passed_time":0.5957766269,"remaining_time":2.353612615},
{"learn":[1.103972317],"iteration":101,"passed_time":0.60260107,"remaining_time":2.351325744},
{"learn":[1.096324426],"iteration":102,"passed_time":0.6056476697,"remaining_time":2.334389562},
{"learn":[1.088907823],"iteration":103,"passed_time":0.6093065017,"remaining_time":2.320051679},
{"learn":[1.075158462],"iteration":104,"passed_time":0.6121344129,"remaining_time":2.302791363},
{"learn":[1.056933373],"iteration":105,"passed_time":0.6185869114,"remaining_time":2.299275878},
{"learn":[1.048956469],"iteration":106,"passed_time":0.6226254815,"remaining_time":2.286839385},
{"learn":[1.042836412],"iteration":107,"passed_time":0.6357455569,"remaining_time":2.30752091},
{"learn":[1.037563859],"iteration":108,"passed_time":0.6431444108,"remaining_time":2.307059309},
{"learn":[1.027501019],"iteration":109,"passed_time":0.6497761819,"remaining_time":2.303751918},
{"learn":[1.021138115],"iteration":110,"passed_time":0.6580136412,"remaining_time":2.306011769},
{"learn":[1.014900918],"iteration":111,"passed_time":0.6636891269,"remaining_time":2.299208761},
{"learn":[1.007875245],"iteration":112,"passed_time":0.6680421751,"remaining_time":2.287896653},
{"learn":[0.9997601531],"iteration":113,"passed_time":0.6709307179,"remaining_time":2.271747869},
{"learn":[0.9850396489],"iteration":114,"passed_time":0.6760370006,"remaining_time":2.263254306},
{"learn":[0.9785574353],"iteration":115,"passed_time":0.6793581546,"remaining_time":2.248909753},
{"learn":[0.971289681],"iteration":116,"passed_time":0.6850073373,"remaining_time":2.242374446},
{"learn":[0.9659173672],"iteration":117,"passed_time":0.6880278667,"remaining_time":2.22734445},
{"learn":[0.9611346855],"iteration":118,"passed_time":0.6898543699,"remaining_time":2.208693403},
{"learn":[0.9561979844],"iteration":119,"passed_time":0.6933906602,"remaining_time":2.195737091},
{"learn":[0.951120922],"iteration":120,"passed_time":0.6965407296,"remaining_time":2.181726748},
{"learn":[0.944441057],"iteration":121,"passed_time":0.6989045243,"remaining_time":2.16545828},
{"learn":[0.9334635409],"iteration":122,"passed_time":0.7028658732,"remaining_time":2.154312473},
{"learn":[0.9288770723],"iteration":123,"passed_time":0.7057704197,"remaining_time":2.140078047},
{"learn":[0.9220543625],"iteration":124,"passed_time":0.7080629507,"remaining_time":2.124188852},
{"learn":[0.9098862408],"iteration":125,"passed_time":0.7110505012,"remaining_time":2.110578472},
{"learn":[0.9053907442],"iteration":126,"passed_time":0.7136092395,"remaining_time":2.095875955},
{"learn":[0.8987165346],"iteration":127,"passed_time":0.7167888572,"remaining_time":2.083167616},
{"learn":[0.8944107746],"iteration":128,"passed_time":0.7188418052,"remaining_time":2.067366742},
{"learn":[0.8825196431],"iteration":129,"passed_time":0.7218473509,"remaining_time":2.054488614},
{"learn":[0.8772089291],"iteration":130,"passed_time":0.7296027416,"remaining_time":2.055140547},
{"learn":[0.8680370529],"iteration":131,"passed_time":0.7359982889,"remaining_time":2.051874017},
{"learn":[0.8637263779],"iteration":132,"passed_time":0.7391712679,"remaining_time":2.039668085},
{"learn":[0.8597849193],"iteration":133,"passed_time":0.7427949224,"remaining_time":2.028827922},
{"learn":[0.855595153],"iteration":134,"passed_time":0.7469705544,"remaining_time":2.019587055},
{"learn":[0.850031675],"iteration":135,"passed_time":0.7508744795,"remaining_time":2.00969346},
{"learn":[0.8453587909],"iteration":136,"passed_time":0.756916475,"remaining_time":2.005552412},
{"learn":[0.8414892243],"iteration":137,"passed_time":0.7616311333,"remaining_time":1.997901958},
{"learn":[0.8368488588],"iteration":138,"passed_time":0.7676284027,"remaining_time":1.993624844},
{"learn":[0.8331929048],"iteration":139,"passed_time":0.7726722197,"remaining_time":1.986871422},
{"learn":[0.8220780119],"iteration":140,"passed_time":0.7783576006,"remaining_time":1.981775735},
{"learn":[0.8178785042],"iteration":141,"passed_time":0.7808631501,"remaining_time":1.968654984},
{"learn":[0.8138083202],"iteration":142,"passed_time":0.784765758,"remaining_time":1.959170459},
{"learn":[0.8045375307],"iteration":143,"passed_time":0.7882144065,"remaining_time":1.948641172},
{"learn":[0.7997664659],"iteration":144,"passed_time":0.7889820877,"remaining_time":1.931645801},
{"learn":[0.7890796206],"iteration":145,"passed_time":0.7918029629,"remaining_time":1.91985102},
{"learn":[0.778145503],"iteration":146,"passed_time":0.7949654713,"remaining_time":1.908998717},
{"learn":[0.7745232685],"iteration":147,"passed_time":0.7973711316,"remaining_time":1.896450259},
{"learn":[0.7702150075],"iteration":148,"passed_time":0.7998067326,"remaining_time":1.884108478},
{"learn":[0.7671099687],"iteration":149,"passed_time":0.8023354237,"remaining_time":1.872115989},
{"learn":[0.7640463838],"iteration":150,"passed_time":0.8057507027,"remaining_time":1.862297982},
{"learn":[0.7608508686],"iteration":151,"passed_time":0.8082597464,"remaining_time":1.850489419},
{"learn":[0.7504431746],"iteration":152,"passed_time":0.8135243148,"remaining_time":1.845051877},
{"learn":[0.7407574571],"iteration":153,"passed_time":0.8166569346,"remaining_time":1.834826619},
{"learn":[0.7376454402],"iteration":154,"passed_time":0.8202159669,"remaining_time":1.825641991},
{"learn":[0.7270306354],"iteration":155,"passed_time":0.8230555867,"remaining_time":1.814943089},
{"learn":[0.7192667687],"iteration":156,"passed_time":0.8258567913,"remaining_time":1.804260379},
{"learn":[0.7163139564],"iteration":157,"passed_time":0.8292826529,"remaining_time":1.79502954},
{"learn":[0.7070093357],"iteration":158,"passed_time":0.8375680516,"remaining_time":1.796293746},
{"learn":[0.7040170075],"iteration":159,"passed_time":0.8436866695,"remaining_time":1.792834173},
{"learn":[0.6961487402],"iteration":160,"passed_time":0.8485417452,"remaining_time":1.786681066},
{"learn":[0.6932834688],"iteration":161,"passed_time":0.8519379859,"remaining_time":1.777500242},
{"learn":[0.6848190551],"iteration":162,"passed_time":0.857540679,"remaining_time":1.772952201},
{"learn":[0.6812940783],"iteration":163,"passed_time":0.8608703308,"remaining_time":1.763734336},
{"learn":[0.6788691376],"iteration":164,"passed_time":0.8695476007,"remaining_time":1.765445129},
{"learn":[0.6706975861],"iteration":165,"passed_time":0.8755857714,"remaining_time":1.761720769},
{"learn":[0.666928348],"iteration":166,"passed_time":0.8780182734,"remaining_time":1.750778952},
{"learn":[0.6643191653],"iteration":167,"passed_time":0.8828914018,"remaining_time":1.74476158},
{"learn":[0.6611107926],"iteration":168,"passed_time":0.886841555,"remaining_time":1.736950028},
{"learn":[0.652250824],"iteration":169,"passed_time":0.8922856184,"remaining_time":1.732083847},
{"learn":[0.6455639574],"iteration":170,"passed_time":0.8943640792,"remaining_time":1.720735568},
{"learn":[0.6373448164],"iteration":171,"passed_time":0.8981689156,"remaining_time":1.712787234},
{"learn":[0.6350855746],"iteration":172,"passed_time":0.9012336323,"remaining_time":1.703487848},
{"learn":[0.6315533387],"iteration":173,"passed_time":0.9054421793,"remaining_time":1.696403164},
{"learn":[0.6280774616],"iteration":174,"passed_time":0.9078844931,"remaining_time":1.686071202},
{"learn":[0.6214304878],"iteration":175,"passed_time":0.9133586941,"remaining_time":1.681410323},
{"learn":[0.6184052697],"iteration":176,"passed_time":0.9171000759,"remaining_time":1.673578105},
{"learn":[0.6115302755],"iteration":177,"passed_time":0.9218608397,"remaining_time":1.667635901},
{"learn":[0.6084104012],"iteration":178,"passed_time":0.9252230343,"remaining_time":1.659198849},
{"learn":[0.6063655309],"iteration":179,"passed_time":0.930371726,"remaining_time":1.65399418},
{"learn":[0.6044450008],"iteration":180,"passed_time":0.9354862382,"remaining_time":1.648729889},
{"learn":[0.6026096131],"iteration":181,"passed_time":0.9410840697,"remaining_time":1.644311726},
{"learn":[0.5961853507],"iteration":182,"passed_time":0.943804786,"remaining_time":1.634896815},
{"learn":[0.5935139339],"iteration":183,"passed_time":0.9473977458,"remaining_time":1.62705265},
{"learn":[0.5861190331],"iteration":184,"passed_time":0.9518545534,"remaining_time":1.620725321},
{"learn":[0.5843187905],"iteration":185,"passed_time":0.9567151259,"remaining_time":1.615099729},
{"learn":[0.5822994705],"iteration":186,"passed_time":0.9640316245,"remaining_time":1.61359304},
{"learn":[0.5766234628],"iteration":187,"passed_time":0.9700597916,"remaining_time":1.609886463},
{"learn":[0.5712922047],"iteration":188,"passed_time":0.9727328303,"remaining_time":1.600634446},
{"learn":[0.5696369561],"iteration":189,"passed_time":0.9753351045,"remaining_time":1.591336223},
{"learn":[0.5670917926],"iteration":190,"passed_time":0.9779235754,"remaining_time":1.582085784},
{"learn":[0.5655079637],"iteration":191,"passed_time":0.9801534206,"remaining_time":1.572329445},
{"learn":[0.5603276864],"iteration":192,"passed_time":0.9854239712,"remaining_time":1.567487871},
{"learn":[0.5558457208],"iteration":193,"passed_time":0.9883738375,"remaining_time":1.558981414},
{"learn":[0.5543573593],"iteration":194,"passed_time":0.9921494131,"remaining_time":1.551823441},
{"learn":[0.5503353588],"iteration":195,"passed_time":0.9932980302,"remaining_time":1.540625516},
{"learn":[0.5485329147],"iteration":196,"passed_time":0.9976053207,"remaining_time":1.534387879},
{"learn":[0.5451952684],"iteration":197,"passed_time":0.9997102749,"remaining_time":1.524810621},
{"learn":[0.5438283265],"iteration":198,"passed_time":1.004769183,"remaining_time":1.519776502},
{"learn":[0.5424531563],"iteration":199,"passed_time":1.007039576,"remaining_time":1.510559365},
{"learn":[0.5411622014],"iteration":200,"passed_time":1.011160004,"remaining_time":1.504163388},
{"learn":[0.5396127467],"iteration":201,"passed_time":1.013630564,"remaining_time":1.49535598},
{"learn":[0.5382011959],"iteration":202,"passed_time":1.016809083,"remaining_time":1.487646787},
{"learn":[0.5344875077],"iteration":203,"passed_time":1.021140247,"remaining_time":1.481654476},
{"learn":[0.5326546898],"iteration":204,"passed_time":1.02564423,"remaining_time":1.475927063},
{"learn":[0.5278872059],"iteration":205,"passed_time":1.033079938,"remaining_time":1.47439564},
{"learn":[0.5262428857],"iteration":206,"passed_time":1.039160326,"remaining_time":1.470888771},
{"learn":[0.519520931],"iteration":207,"passed_time":1.043490536,"remaining_time":1.464900175},
{"learn":[0.515131576],"iteration":208,"passed_time":1.04930677,"remaining_time":1.460996507},
{"learn":[0.5141556255],"iteration":209,"passed_time":1.053577488,"remaining_time":1.454940341},
{"learn":[0.5126415102],"iteration":210,"passed_time":1.056421359,"remaining_time":1.44694679},
{"learn":[0.5112366985],"iteration":211,"passed_time":1.062015681,"remaining_time":1.442738283},
{"learn":[0.507113817],"iteration":212,"passed_time":1.073467996,"remaining_time":1.446409929},
{"learn":[0.5056370564],"iteration":213,"passed_time":1.081965373,"remaining_time":1.445991105},
{"learn":[0.5005601508],"iteration":214,"passed_time":1.086431332,"remaining_time":1.44015316},
{"learn":[0.4992774801],"iteration":215,"passed_time":1.091541577,"remaining_time":1.435175037},
{"learn":[0.4971012547],"iteration":216,"passed_time":1.095796424,"remaining_time":1.429080129},
{"learn":[0.4929672164],"iteration":217,"passed_time":1.103735981,"remaining_time":1.427768562},
{"learn":[0.4916508852],"iteration":218,"passed_time":1.112016757,"remaining_time":1.426834287},
{"learn":[0.4884120848],"iteration":219,"passed_time":1.116603337,"remaining_time":1.42113152},
{"learn":[0.4871550001],"iteration":220,"passed_time":1.126755247,"remaining_time":1.422464769},
{"learn":[0.4859919166],"iteration":221,"passed_time":1.131550287,"remaining_time":1.416986395},
{"learn":[0.4837381701],"iteration":222,"passed_time":1.139517364,"remaining_time":1.415454305},
{"learn":[0.4825289812],"iteration":223,"passed_time":1.144631574,"remaining_time":1.410349618},
{"learn":[0.4816467026],"iteration":224,"passed_time":1.146587587,"remaining_time":1.401384829},
{"learn":[0.4764209793],"iteration":225,"passed_time":1.153261183,"remaining_time":1.398201611},
{"learn":[0.475580127],"iteration":226,"passed_time":1.153932463,"remaining_time":1.387768997},
{"learn":[0.4717530668],"iteration":227,"passed_time":1.160536347,"remaining_time":1.384499501},
{"learn":[0.4708128061],"iteration":228,"passed_time":1.168056561,"remaining_time":1.382285275},
{"learn":[0.4665168052],"iteration":229,"passed_time":1.173560233,"remaining_time":1.377657665},
{"learn":[0.4656862073],"iteration":230,"passed_time":1.184038479,"remaining_time":1.378815372},
{"learn":[0.4649807125],"iteration":231,"passed_time":1.188045856,"remaining_time":1.372397799},
{"learn":[0.4617973905],"iteration":232,"passed_time":1.194803062,"remaining_time":1.369152007},
{"learn":[0.4588518163],"iteration":233,"passed_time":1.198497144,"remaining_time":1.362394189},
{"learn":[0.4582005605],"iteration":234,"passed_time":1.206342864,"remaining_time":1.360344081},
{"learn":[0.4543206416],"iteration":235,"passed_time":1.209326962,"remaining_time":1.352806432},
{"learn":[0.4480996361],"iteration":236,"passed_time":1.212683466,"remaining_time":1.345720471},
{"learn":[0.444222121],"iteration":237,"passed_time":1.216396549,"remaining_time":1.339058385},
{"learn":[0.4436222701],"iteration":238,"passed_time":1.220751696,"remaining_time":1.333122145},
{"learn":[0.4424159501],"iteration":239,"passed_time":1.224903497,"remaining_time":1.326978788},
{"learn":[0.4409638815],"iteration":240,"passed_time":1.228529921,"remaining_time":1.320287342},
{"learn":[0.440332661],"iteration":241,"passed_time":1.232804382,"remaining_time":1.314312109},
{"learn":[0.4371961037],"iteration":242,"passed_time":1.235811619,"remaining_time":1.307010642},
{"learn":[0.4338616888],"iteration":243,"passed_time":1.243086326,"remaining_time":1.30422172},
{"learn":[0.4327832158],"iteration":244,"passed_time":1.246859949,"remaining_time":1.297752192},
{"learn":[0.4292706486],"iteration":245,"passed_time":1.250391111,"remaining_time":1.291054237},
{"learn":[0.4269928968],"iteration":246,"passed_time":1.253677834,"remaining_time":1.284131547},
{"learn":[0.4251210266],"iteration":247,"passed_time":1.261119251,"remaining_time":1.281459884},
{"learn":[0.4245662716],"iteration":248,"passed_time":1.268502166,"remaining_time":1.278690938},
{"learn":[0.4240254246],"iteration":249,"passed_time":1.275335465,"remaining_time":1.275335465},
{"learn":[0.4234981405],"iteration":250,"passed_time":1.278992167,"remaining_time":1.268800994},
{"learn":[0.4182434822],"iteration":251,"passed_time":1.283138297,"remaining_time":1.262771022},
{"learn":[0.4163202986],"iteration":252,"passed_time":1.288539251,"remaining_time":1.257981008},
{"learn":[0.4146333239],"iteration":253,"passed_time":1.293253059,"remaining_time":1.25252068},
{"learn":[0.4141391347],"iteration":254,"passed_time":1.299354063,"remaining_time":1.248399001},
{"learn":[0.410070938],"iteration":255,"passed_time":1.304318283,"remaining_time":1.243178364},
{"learn":[0.4094708697],"iteration":256,"passed_time":1.313896813,"remaining_time":1.242322667},
{"learn":[0.4057474964],"iteration":257,"passed_time":1.317709135,"remaining_time":1.235990739},
{"learn":[0.4018459897],"iteration":258,"passed_time":1.323875998,"remaining_time":1.231869172},
{"learn":[0.3978026507],"iteration":259,"passed_time":1.329510903,"remaining_time":1.227240833},
{"learn":[0.3973393306],"iteration":260,"passed_time":1.335858457,"remaining_time":1.223257361},
{"learn":[0.3962625161],"iteration":261,"passed_time":1.337946089,"remaining_time":1.215386142},
{"learn":[0.3957300734],"iteration":262,"passed_time":1.341259331,"remaining_time":1.208663352},
{"learn":[0.3935492496],"iteration":263,"passed_time":1.345523096,"remaining_time":1.202816101},
{"learn":[0.3907738144],"iteration":264,"passed_time":1.347642937,"remaining_time":1.195079586},
{"learn":[0.3883436239],"iteration":265,"passed_time":1.350121067,"remaining_time":1.187700487},
{"learn":[0.3840778869],"iteration":266,"passed_time":1.352237884,"remaining_time":1.180042798},
{"learn":[0.3810250913],"iteration":267,"passed_time":1.354697926,"remaining_time":1.172723578},
{"learn":[0.3793106884],"iteration":268,"passed_time":1.357220277,"remaining_time":1.165493993},
{"learn":[0.3788177306],"iteration":269,"passed_time":1.360714107,"remaining_time":1.159126832},
{"learn":[0.3751355184],"iteration":270,"passed_time":1.364166914,"remaining_time":1.152746211},
{"learn":[0.3746750877],"iteration":271,"passed_time":1.367007505,"remaining_time":1.145873938},
{"learn":[0.3712190726],"iteration":272,"passed_time":1.370429493,"remaining_time":1.139514633},
{"learn":[0.3691324967],"iteration":273,"passed_time":1.374457453,"remaining_time":1.133676586},
{"learn":[0.3687880864],"iteration":274,"passed_time":1.378013713,"remaining_time":1.127465765},
{"learn":[0.3678008933],"iteration":275,"passed_time":1.381156061,"remaining_time":1.120938252},
{"learn":[0.3647921761],"iteration":276,"passed_time":1.384067536,"remaining_time":1.114249316},
{"learn":[0.3631705707],"iteration":277,"passed_time":1.387797222,"remaining_time":1.108240947},
{"learn":[0.3594860427],"iteration":278,"passed_time":1.391757898,"remaining_time":1.102431883},
{"learn":[0.3551247408],"iteration":279,"passed_time":1.394516722,"remaining_time":1.09569171},
{"learn":[0.3540118055],"iteration":280,"passed_time":1.398392489,"remaining_time":1.089850374},
{"learn":[0.353573603],"iteration":281,"passed_time":1.400669042,"remaining_time":1.082786706},
{"learn":[0.3505496241],"iteration":282,"passed_time":1.403449829,"remaining_time":1.076143508},
{"learn":[0.350164171],"iteration":283,"passed_time":1.406013757,"remaining_time":1.069362576},
{"learn":[0.3497909455],"iteration":284,"passed_time":1.408883458,"remaining_time":1.062841907},
{"learn":[0.3494136861],"iteration":285,"passed_time":1.412533761,"remaining_time":1.056930856},
{"learn":[0.346566179],"iteration":286,"passed_time":1.41550272,"remaining_time":1.050529893},
{"learn":[0.3455621596],"iteration":287,"passed_time":1.420896523,"remaining_time":1.045937718},
{"learn":[0.3436005677],"iteration":288,"passed_time":1.425771473,"remaining_time":1.04096118},
{"learn":[0.3411654579],"iteration":289,"passed_time":1.429435323,"remaining_time":1.035108337},
{"learn":[0.3383190303],"iteration":290,"passed_time":1.433652133,"remaining_time":1.029667683},
{"learn":[0.3363944841],"iteration":291,"passed_time":1.437820504,"remaining_time":1.024200907},
{"learn":[0.3360729182],"iteration":292,"passed_time":1.442830019,"remaining_time":1.019337249},
{"learn":[0.3330513833],"iteration":293,"passed_time":1.446908225,"remaining_time":1.013820049},
{"learn":[0.3301695298],"iteration":294,"passed_time":1.452185689,"remaining_time":1.009145987},
{"learn":[0.3273257469],"iteration":295,"passed_time":1.455929967,"remaining_time":1.003411193},
{"learn":[0.3255934767],"iteration":296,"passed_time":1.461023176,"remaining_time":0.9986118003},
{"learn":[0.3225383624],"iteration":297,"passed_time":1.466728029,"remaining_time":0.9942250397},
{"learn":[0.3194852069],"iteration":298,"passed_time":1.473287047,"remaining_time":0.9904036667},
{"learn":[0.3183648566],"iteration":299,"passed_time":1.475148947,"remaining_time":0.983432631},
{"learn":[0.3170062647],"iteration":300,"passed_time":1.484827806,"remaining_time":0.9816635664},
{"learn":[0.3141331355],"iteration":301,"passed_time":1.487628934,"remaining_time":0.9753328774},
{"learn":[0.3112705841],"iteration":302,"passed_time":1.491732838,"remaining_time":0.9698725051},
{"learn":[0.3088164979],"iteration":303,"passed_time":1.497570653,"remaining_time":0.9655389737},
{"learn":[0.305807267],"iteration":304,"passed_time":1.502676285,"remaining_time":0.9607274612},
{"learn":[0.3036542855],"iteration":305,"passed_time":1.504710194,"remaining_time":0.9539665936},
{"learn":[0.3016119238],"iteration":306,"passed_time":1.508640988,"remaining_time":0.9484290249},
{"learn":[0.2998042174],"iteration":307,"passed_time":1.512992272,"remaining_time":0.9431640137},
{"learn":[0.2970371778],"iteration":308,"passed_time":1.520372347,"remaining_time":0.9397770816},
{"learn":[0.2952227157],"iteration":309,"passed_time":1.5237266,"remaining_time":0.9338969483},
{"learn":[0.2949285774],"iteration":310,"passed_time":1.5275138,"remaining_time":0.928296168},
{"learn":[0.2927328278],"iteration":311,"passed_time":1.535110294,"remaining_time":0.9250023569},
{"learn":[0.2904621222],"iteration":312,"passed_time":1.539799612,"remaining_time":0.919944177},
{"learn":[0.2891764349],"iteration":313,"passed_time":1.544374101,"remaining_time":0.9148203274},
{"learn":[0.2875202218],"iteration":314,"passed_time":1.547610657,"remaining_time":0.9089141951},
{"learn":[0.2849151213],"iteration":315,"passed_time":1.550295313,"remaining_time":0.9027035998},
{"learn":[0.2845893988],"iteration":316,"passed_time":1.554910344,"remaining_time":0.8976296309},
{"learn":[0.282203408],"iteration":317,"passed_time":1.557455378,"remaining_time":0.8913738329},
{"learn":[0.2800102602],"iteration":318,"passed_time":1.562897266,"remaining_time":0.8867849689},
{"learn":[0.2777258115],"iteration":319,"passed_time":1.56569081,"remaining_time":0.8807010809},
{"learn":[0.2749156325],"iteration":320,"passed_time":1.572319457,"remaining_time":0.8767762702},
{"learn":[0.2720909614],"iteration":321,"passed_time":1.579870438,"remaining_time":0.8733445276},
{"learn":[0.2698716102],"iteration":322,"passed_time":1.586414019,"remaining_time":0.8693352363},
{"learn":[0.2694810528],"iteration":323,"passed_time":1.591133805,"remaining_time":0.8643195978},
{"learn":[0.2691732177],"iteration":324,"passed_time":1.594509925,"remaining_time":0.8585822674},
{"learn":[0.2678532241],"iteration":325,"passed_time":1.59922925,"remaining_time":0.853576348},
{"learn":[0.2675367189],"iteration":326,"passed_time":1.602795034,"remaining_time":0.8479618988},
{"learn":[0.2673162653],"iteration":327,"passed_time":1.607742391,"remaining_time":0.8430844246},
{"learn":[0.2665526519],"iteration":328,"passed_time":1.613268977,"remaining_time":0.8385075838},
{"learn":[0.2654116455],"iteration":329,"passed_time":1.618484127,"remaining_time":0.8337645505},
{"learn":[0.2651633173],"iteration":330,"passed_time":1.624919345,"remaining_time":0.8296415992},
{"learn":[0.2622428701],"iteration":331,"passed_time":1.627733749,"remaining_time":0.8236724995},
{"learn":[0.2601908985],"iteration":332,"passed_time":1.630805255,"remaining_time":0.8178512842},
{"learn":[0.2580187828],"iteration":333,"passed_time":1.633432744,"remaining_time":0.8118258548},
{"learn":[0.2562443484],"iteration":334,"passed_time":1.636307917,"remaining_time":0.8059427053},
{"learn":[0.2534594198],"iteration":335,"passed_time":1.639544276,"remaining_time":0.8002537537},
{"learn":[0.2522359424],"iteration":336,"passed_time":1.64240061,"remaining_time":0.7943955474},
{"learn":[0.2507348923],"iteration":337,"passed_time":1.646498012,"remaining_time":0.789149935},
{"learn":[0.2487755401],"iteration":338,"passed_time":1.651163207,"remaining_time":0.7841807563},
{"learn":[0.2463742548],"iteration":339,"passed_time":1.657382865,"remaining_time":0.7799448775},
{"learn":[0.2446170656],"iteration":340,"passed_time":1.660052002,"remaining_time":0.7740418426},
{"learn":[0.2419674272],"iteration":341,"passed_time":1.665633891,"remaining_time":0.7695033766},
{"learn":[0.2400226955],"iteration":342,"passed_time":1.669810009,"remaining_time":0.7643153684},
{"learn":[0.2391071867],"iteration":343,"passed_time":1.674528152,"remaining_time":0.7593790457},
{"learn":[0.2366376028],"iteration":344,"passed_time":1.67825106,"remaining_time":0.753996853},
{"learn":[0.2354110673],"iteration":345,"passed_time":1.681922737,"remaining_time":0.7486014493},
{"learn":[0.2336104013],"iteration":346,"passed_time":1.687966931,"remaining_time":0.7442620761},
{"learn":[0.2316127107],"iteration":347,"passed_time":1.693752971,"remaining_time":0.7398001483},
{"learn":[0.230672155],"iteration":348,"passed_time":1.699572744,"remaining_time":0.7353452275},
{"learn":[0.2287937831],"iteration":349,"passed_time":1.703368921,"remaining_time":0.730015252},
{"learn":[0.2280331806],"iteration":350,"passed_time":1.708890446,"remaining_time":0.7254264288},
{"learn":[0.2260144396],"iteration":351,"passed_time":1.710506508,"remaining_time":0.7191902365},
{"learn":[0.2245941267],"iteration":352,"passed_time":1.716822512,"remaining_time":0.7149374199},
{"learn":[0.2227173514],"iteration":353,"passed_time":1.719396179,"remaining_time":0.7091294976},
{"learn":[0.2218847919],"iteration":354,"passed_time":1.72483809,"remaining_time":0.7045113326},
{"learn":[0.2197424488],"iteration":355,"passed_time":1.727788493,"remaining_time":0.6988807385},
{"learn":[0.2179253615],"iteration":356,"passed_time":1.733254926,"remaining_time":0.6942729814},
{"learn":[0.2154983362],"iteration":357,"passed_time":1.737443528,"remaining_time":0.6891535781},
{"learn":[0.213882863],"iteration":358,"passed_time":1.741896452,"remaining_time":0.6841431748},
{"learn":[0.2119899493],"iteration":359,"passed_time":1.749109562,"remaining_time":0.6802092743},
{"learn":[0.2100186948],"iteration":360,"passed_time":1.753427971,"remaining_time":0.6751426261},
{"learn":[0.208768569],"iteration":361,"passed_time":1.761672276,"remaining_time":0.6715767239},
{"learn":[0.2071161958],"iteration":362,"passed_time":1.763279808,"remaining_time":0.665480258},
{"learn":[0.2058181307],"iteration":363,"passed_time":1.768124246,"remaining_time":0.6606178503},
{"learn":[0.2039405469],"iteration":364,"passed_time":1.776272506,"remaining_time":0.6569775023},
{"learn":[0.2020626891],"iteration":365,"passed_time":1.781091286,"remaining_time":0.6520935308},
{"learn":[0.2006840875],"iteration":366,"passed_time":1.78449795,"remaining_time":0.6466981671},
{"learn":[0.1991322412],"iteration":367,"passed_time":1.78961345,"remaining_time":0.6419265635},
{"learn":[0.1978319009],"iteration":368,"passed_time":1.794913454,"remaining_time":0.6372185977},
{"learn":[0.1962909914],"iteration":369,"passed_time":1.798840029,"remaining_time":0.632024875},
{"learn":[0.1959286402],"iteration":370,"passed_time":1.802634032,"remaining_time":0.6267918873},
{"learn":[0.1944913744],"iteration":371,"passed_time":1.805989842,"remaining_time":0.6214158597},
{"learn":[0.1936904383],"iteration":372,"passed_time":1.809622373,"remaining_time":0.616144883},
{"learn":[0.1922440967],"iteration":373,"passed_time":1.8117891,"remaining_time":0.6103888413},
{"learn":[0.1901687531],"iteration":374,"passed_time":1.816364292,"remaining_time":0.6054547641},
{"learn":[0.188996179],"iteration":375,"passed_time":1.820860262,"remaining_time":0.6004964694},
{"learn":[0.1878037788],"iteration":376,"passed_time":1.824859411,"remaining_time":0.5953785345},
{"learn":[0.1863847811],"iteration":377,"passed_time":1.827670351,"remaining_time":0.5898830233},
{"learn":[0.1857303903],"iteration":378,"passed_time":1.833604101,"remaining_time":0.5853986707},
{"learn":[0.1847456988],"iteration":379,"passed_time":1.84013207,"remaining_time":0.581094338},
{"learn":[0.1836504147],"iteration":380,"passed_time":1.844205522,"remaining_time":0.5760116985},
{"learn":[0.1826315594],"iteration":381,"passed_time":1.851700883,"remaining_time":0.5719913722},
{"learn":[0.1808144657],"iteration":382,"passed_time":1.857289808,"remaining_time":0.5673705159},
{"learn":[0.1802510858],"iteration":383,"passed_time":1.859991409,"remaining_time":0.5618724047},
{"learn":[0.1794728364],"iteration":384,"passed_time":1.864426001,"remaining_time":0.5569064679},
{"learn":[0.1780346116],"iteration":385,"passed_time":1.868679645,"remaining_time":0.5518898433},
{"learn":[0.177459103],"iteration":386,"passed_time":1.873593746,"remaining_time":0.5470700085},
{"learn":[0.1760920121],"iteration":387,"passed_time":1.876370113,"remaining_time":0.5416326099},
{"learn":[0.1748533252],"iteration":388,"passed_time":1.882491074,"remaining_time":0.5371632627},
{"learn":[0.1734570377],"iteration":389,"passed_time":1.888461265,"remaining_time":0.5326429209},
{"learn":[0.1732148565],"iteration":390,"passed_time":1.893129886,"remaining_time":0.5277523211},
{"learn":[0.1723385358],"iteration":391,"passed_time":1.896635544,"remaining_time":0.5225424459},
{"learn":[0.1716430422],"iteration":392,"passed_time":1.899792806,"remaining_time":0.5172463873},
{"learn":[0.1704704285],"iteration":393,"passed_time":1.905435978,"remaining_time":0.5126299838},
{"learn":[0.169837773],"iteration":394,"passed_time":1.909449644,"remaining_time":0.5075752219},
{"learn":[0.1680879688],"iteration":395,"passed_time":1.913775219,"remaining_time":0.5026076332},
{"learn":[0.167557129],"iteration":396,"passed_time":1.918956036,"remaining_time":0.4978651681},
{"learn":[0.1665500098],"iteration":397,"passed_time":1.922419339,"remaining_time":0.4926803331},
{"learn":[0.1663241126],"iteration":398,"passed_time":1.92625316,"remaining_time":0.4875979177},
{"learn":[0.1645105024],"iteration":399,"passed_time":1.928395752,"remaining_time":0.4820989379},
{"learn":[0.1640599971],"iteration":400,"passed_time":1.933618907,"remaining_time":0.4773772364},
{"learn":[0.1626323968],"iteration":401,"passed_time":1.938835615,"remaining_time":0.4726514682},
{"learn":[0.1619094816],"iteration":402,"passed_time":1.942276903,"remaining_time":0.4674959295},
{"learn":[0.1617786878],"iteration":403,"passed_time":1.948002428,"remaining_time":0.4628916661},
{"learn":[0.1613140017],"iteration":404,"passed_time":1.953028351,"remaining_time":0.4581177612},
{"learn":[0.1605008536],"iteration":405,"passed_time":1.959525433,"remaining_time":0.4536832284},
{"learn":[0.1593239225],"iteration":406,"passed_time":1.962412282,"remaining_time":0.4484136172},
{"learn":[0.1579686],"iteration":407,"passed_time":1.965935644,"remaining_time":0.4432992139},
{"learn":[0.1569051375],"iteration":408,"passed_time":1.970876169,"remaining_time":0.4385079007},
{"learn":[0.1555682612],"iteration":409,"passed_time":1.973264917,"remaining_time":0.4331557136},
{"learn":[0.1546579043],"iteration":410,"passed_time":1.978231012,"remaining_time":0.4283760586},
{"learn":[0.1537136677],"iteration":411,"passed_time":1.983033737,"remaining_time":0.4235606041},
{"learn":[0.1527011697],"iteration":412,"passed_time":1.989016593,"remaining_time":0.4189938102},
{"learn":[0.1524893135],"iteration":413,"passed_time":1.995939272,"remaining_time":0.4146154043},
{"learn":[0.1518975599],"iteration":414,"passed_time":1.997642626,"remaining_time":0.4091557186},
{"learn":[0.1511333431],"iteration":415,"passed_time":2.000896581,"remaining_time":0.4040271942},
{"learn":[0.1510209034],"iteration":416,"passed_time":2.003126433,"remaining_time":0.3987038224},
{"learn":[0.1502640828],"iteration":417,"passed_time":2.005110806,"remaining_time":0.3933470959},
{"learn":[0.1495130865],"iteration":418,"passed_time":2.007679787,"remaining_time":0.3881194815},
{"learn":[0.1486052143],"iteration":419,"passed_time":2.00996042,"remaining_time":0.3828496037},
{"learn":[0.1480649289],"iteration":420,"passed_time":2.012043264,"remaining_time":0.3775568119},
{"learn":[0.1476370625],"iteration":421,"passed_time":2.014985588,"remaining_time":0.3724380945},
{"learn":[0.1467787826],"iteration":422,"passed_time":2.016807997,"remaining_time":0.3671258056},
{"learn":[0.1459566739],"iteration":423,"passed_time":2.018138426,"remaining_time":0.3617417934},
{"learn":[0.1454234519],"iteration":424,"passed_time":2.019746849,"remaining_time":0.3564259145},
{"learn":[0.1442233049],"iteration":425,"passed_time":2.021258361,"remaining_time":0.3511106073},
{"learn":[0.1435225099],"iteration":426,"passed_time":2.022343172,"remaining_time":0.3457401676},
{"learn":[0.1421118978],"iteration":427,"passed_time":2.024057649,"remaining_time":0.3404956793},
{"learn":[0.14139832],"iteration":428,"passed_time":2.025277358,"remaining_time":0.3351857633},
{"learn":[0.1403560744],"iteration":429,"passed_time":2.02720681,"remaining_time":0.3300104109},
{"learn":[0.1398335247],"iteration":430,"passed_time":2.029192386,"remaining_time":0.3248591059},
{"learn":[0.1392963182],"iteration":431,"passed_time":2.031418605,"remaining_time":0.319760336},
{"learn":[0.1390731037],"iteration":432,"passed_time":2.033008784,"remaining_time":0.3145764169},
{"learn":[0.138817546],"iteration":433,"passed_time":2.03492672,"remaining_time":0.3094589021},
{"learn":[0.1377101226],"iteration":434,"passed_time":2.036259541,"remaining_time":0.3042686671},
{"learn":[0.1367141097],"iteration":435,"passed_time":2.037498761,"remaining_time":0.299082387},
{"learn":[0.1361414907],"iteration":436,"passed_time":2.038876122,"remaining_time":0.2939340862},
{"learn":[0.1357727727],"iteration":437,"passed_time":2.040142559,"remaining_time":0.2887873029},
{"learn":[0.134834765],"iteration":438,"passed_time":2.041464239,"remaining_time":0.2836658738},
{"learn":[0.1345572076],"iteration":439,"passed_time":2.043093752,"remaining_time":0.2786036935},
{"learn":[0.1333914119],"iteration":440,"passed_time":2.04556242,"remaining_time":0.2736693486},
{"learn":[0.1323463446],"iteration":441,"passed_time":2.047191361,"remaining_time":0.2686359704},
{"learn":[0.1312981332],"iteration":442,"passed_time":2.048858506,"remaining_time":0.2636228777},
{"learn":[0.130414801],"iteration":443,"passed_time":2.050812291,"remaining_time":0.2586610097},
{"learn":[0.1299835868],"iteration":444,"passed_time":2.052568326,"remaining_time":0.25368822},
{"learn":[0.1293668601],"iteration":445,"passed_time":2.054677365,"remaining_time":0.2487725958},
{"learn":[0.1283077556],"iteration":446,"passed_time":2.056338794,"remaining_time":0.2438164566},
{"learn":[0.127906514],"iteration":447,"passed_time":2.05734973,"remaining_time":0.2387995222},
{"learn":[0.1269966228],"iteration":448,"passed_time":2.060039944,"remaining_time":0.233991174},
{"learn":[0.1261157698],"iteration":449,"passed_time":2.062485028,"remaining_time":0.2291650031},
{"learn":[0.1258389393],"iteration":450,"passed_time":2.064716844,"remaining_time":0.2243262203},
{"learn":[0.1250805755],"iteration":451,"passed_time":2.066931631,"remaining_time":0.2194971643},
{"learn":[0.1242846478],"iteration":452,"passed_time":2.068361101,"remaining_time":0.2145981716},
{"learn":[0.1237706167],"iteration":453,"passed_time":2.069885734,"remaining_time":0.2097241052},
{"learn":[0.1235548232],"iteration":454,"passed_time":2.071092154,"remaining_time":0.2048332899},
{"learn":[0.122489484],"iteration":455,"passed_time":2.073044762,"remaining_time":0.2000306349},
{"learn":[0.1216144751],"iteration":456,"passed_time":2.074989135,"remaining_time":0.1952396779},
{"learn":[0.1211899197],"iteration":457,"passed_time":2.076795765,"remaining_time":0.19044852},
{"learn":[0.1211116609],"iteration":458,"passed_time":2.078144493,"remaining_time":0.1856294645},
{"learn":[0.1201253354],"iteration":459,"passed_time":2.079682136,"remaining_time":0.1808419248},
{"learn":[0.120057632],"iteration":460,"passed_time":2.081098865,"remaining_time":0.1760582553},
{"learn":[0.1199704178],"iteration":461,"passed_time":2.083363494,"remaining_time":0.1713589021},
{"learn":[0.1197202643],"iteration":462,"passed_time":2.085814158,"remaining_time":0.1666849327},
{"learn":[0.1190007075],"iteration":463,"passed_time":2.087122738,"remaining_time":0.1619319365},
{"learn":[0.1183031858],"iteration":464,"passed_time":2.08867725,"remaining_time":0.1572122661},
{"learn":[0.1176643668],"iteration":465,"passed_time":2.09035179,"remaining_time":0.1525149375},
{"learn":[0.1166940509],"iteration":466,"passed_time":2.092133986,"remaining_time":0.1478381618},
{"learn":[0.1160568154],"iteration":467,"passed_time":2.093876847,"remaining_time":0.1431710664},
{"learn":[0.115396837],"iteration":468,"passed_time":2.095162415,"remaining_time":0.138486215},
{"learn":[0.1146625038],"iteration":469,"passed_time":2.097493165,"remaining_time":0.1338825425},
{"learn":[0.1139728854],"iteration":470,"passed_time":2.099439478,"remaining_time":0.1292648511},
{"learn":[0.1131288948],"iteration":471,"passed_time":2.101556022,"remaining_time":0.1246685776},
{"learn":[0.1129319473],"iteration":472,"passed_time":2.108309317,"remaining_time":0.1203474663},
{"learn":[0.1127074023],"iteration":473,"passed_time":2.110479738,"remaining_time":0.1157647113},
{"learn":[0.1119912004],"iteration":474,"passed_time":2.11282117,"remaining_time":0.1112011142},
{"learn":[0.1111945496],"iteration":475,"passed_time":2.113964977,"remaining_time":0.1065864694},
{"learn":[0.1109726856],"iteration":476,"passed_time":2.114909384,"remaining_time":0.1019767627},
{"learn":[0.1103594041],"iteration":477,"passed_time":2.116264837,"remaining_time":0.09740131051},
{"learn":[0.1098419042],"iteration":478,"passed_time":2.117319517,"remaining_time":0.09282611663},
{"learn":[0.1090109616],"iteration":479,"passed_time":2.118207104,"remaining_time":0.08825862935},
{"learn":[0.1083150661],"iteration":480,"passed_time":2.119021735,"remaining_time":0.08370356126},
{"learn":[0.1076200069],"iteration":481,"passed_time":2.119830561,"remaining_time":0.07916379689},
{"learn":[0.1073633784],"iteration":482,"passed_time":2.120703868,"remaining_time":0.07464175105},
{"learn":[0.1070715531],"iteration":483,"passed_time":2.121545558,"remaining_time":0.07013373744},
{"learn":[0.1065932697],"iteration":484,"passed_time":2.122967796,"remaining_time":0.0656587978},
{"learn":[0.1064696335],"iteration":485,"passed_time":2.123801357,"remaining_time":0.06117946295},
{"learn":[0.1058393183],"iteration":486,"passed_time":2.124671654,"remaining_time":0.05671608112},
{"learn":[0.1050557122],"iteration":487,"passed_time":2.125511777,"remaining_time":0.05226668305},
{"learn":[0.1043827472],"iteration":488,"passed_time":2.126502034,"remaining_time":0.04783542408},
{"learn":[0.1037972223],"iteration":489,"passed_time":2.127325891,"remaining_time":0.0434148141},
{"learn":[0.1029680257],"iteration":490,"passed_time":2.129917094,"remaining_time":0.03904125019},
{"learn":[0.1025091676],"iteration":491,"passed_time":2.131015246,"remaining_time":0.0346506544},
{"learn":[0.1018091084],"iteration":492,"passed_time":2.132033275,"remaining_time":0.03027227774},
{"learn":[0.1013567557],"iteration":493,"passed_time":2.132999195,"remaining_time":0.02590687281},
{"learn":[0.1005806191],"iteration":494,"passed_time":2.134326842,"remaining_time":0.02155885699},
{"learn":[0.09982919158],"iteration":495,"passed_time":2.13516861,"remaining_time":0.0172191017},
{"learn":[0.09962881772],"iteration":496,"passed_time":2.136226495,"remaining_time":0.01289472734},
{"learn":[0.0990364125],"iteration":497,"passed_time":2.137241941,"remaining_time":0.008583300969},
{"learn":[0.09853197031],"iteration":498,"passed_time":2.138228805,"remaining_time":0.004285027666},
{"learn":[0.09832135825],"iteration":499,"passed_time":2.139094656,"remaining_time":0}
]}iteration":499,"passed_time":2.086244199,"remaining_time":0}
]}:[0.0919883031],"iteration":499,"passed_time":1.982516334,"remaining_time":0}
]}2,"remaining_time":0.003074186236},
{"learn":[0.08621319835],"iteration":499,"passed_time":1.536201986,"remaining_time":0}
]}